{"name":"Abrir la URL, loguearse y navegar a agent","id":"apertura-de-la-pagina-de-casos;abrir-la-url--loguearse-y-navegar-a-agent","testSteps":[{"number":1,"description":"Given el actor tiene un navegador disponible","duration":44,"startTime":"2026-05-05T11:24:27.058883-05:00[America/Bogota]","result":"SUCCESS","precondition":false,"level":0},{"number":2,"description":"When abre la pagina de casos","duration":11661,"startTime":"2026-05-05T11:24:27.106878400-05:00[America/Bogota]","screenshots":[{"screenshot":"ac1e6c390a60cf01bafd61b0f412d1e32b0b8ae3b6829148ee8a53edc4fc084a.png","timeStamp":1777998278767,"screenshotName":"ac1e6c390a60cf01bafd61b0f412d1e32b0b8ae3b6829148ee8a53edc4fc084a.png"}],"result":"SUCCESS","precondition":false,"level":0,"children":[{"number":3,"description":"Abre la pagina de casos","duration":11372,"startTime":"2026-05-05T11:24:27.385820100-05:00[America/Bogota]","screenshots":[{"screenshot":"ac1e6c390a60cf01bafd61b0f412d1e32b0b8ae3b6829148ee8a53edc4fc084a.png","timeStamp":1777998278758,"screenshotName":"ac1e6c390a60cf01bafd61b0f412d1e32b0b8ae3b6829148ee8a53edc4fc084a.png"}],"result":"SUCCESS","precondition":false,"level":1,"children":[{"number":4,"description":"Sara opens the browser at https://us-east-1s66ymlwwk.auth.us-east-1.amazoncognito.com/login?client_id\u003d2hfo5293cfbh1h9fbe9m7g07dn\u0026response_type\u003dcode\u0026scope\u003demail+openid+profile\u0026redirect_uri\u003dhttps%3A%2F%2Fasistenciaapp.kit.sura-konecta.com%2Fauth","duration":11333,"startTime":"2026-05-05T11:24:27.412821200-05:00[America/Bogota]","screenshots":[{"screenshot":"ac1e6c390a60cf01bafd61b0f412d1e32b0b8ae3b6829148ee8a53edc4fc084a.png","timeStamp":1777998278744,"screenshotName":"ac1e6c390a60cf01bafd61b0f412d1e32b0b8ae3b6829148ee8a53edc4fc084a.png"}],"result":"SUCCESS","precondition":false,"level":2}]}]},{"number":5,"description":"And realiza login con credenciales","duration":23528,"startTime":"2026-05-05T11:24:38.768994300-05:00[America/Bogota]","screenshots":[{"screenshot":"0725a4f626bfee864fee03c7244afec4f395c08e6c1381211742ea81ff8fb28c.png","timeStamp":1777998302296,"screenshotName":"0725a4f626bfee864fee03c7244afec4f395c08e6c1381211742ea81ff8fb28c.png"}],"result":"SUCCESS","precondition":false,"level":0,"children":[{"number":6,"description":"Login con Cognito usando credenciales","duration":23493,"startTime":"2026-05-05T11:24:38.789996800-05:00[America/Bogota]","screenshots":[{"screenshot":"0725a4f626bfee864fee03c7244afec4f395c08e6c1381211742ea81ff8fb28c.png","timeStamp":1777998302283,"screenshotName":"0725a4f626bfee864fee03c7244afec4f395c08e6c1381211742ea81ff8fb28c.png"}],"result":"SUCCESS","precondition":false,"level":1,"children":[{"number":7,"description":"Sara opens the browser at https://us-east-1s66ymlwwk.auth.us-east-1.amazoncognito.com/login?client_id\u003d2hfo5293cfbh1h9fbe9m7g07dn\u0026response_type\u003dcode\u0026scope\u003demail+openid+profile\u0026redirect_uri\u003dhttps%3A%2F%2Fasistenciaapp.kit.sura-konecta.com%2Fauth","duration":493,"startTime":"2026-05-05T11:24:38.795721300-05:00[America/Bogota]","screenshots":[{"screenshot":"ac1e6c390a60cf01bafd61b0f412d1e32b0b8ae3b6829148ee8a53edc4fc084a.png","timeStamp":1777998279288,"screenshotName":"ac1e6c390a60cf01bafd61b0f412d1e32b0b8ae3b6829148ee8a53edc4fc084a.png"}],"result":"SUCCESS","precondition":false,"level":2},{"number":8,"description":"Sara enters \u0027BOT01\u0027 into cognito username field","duration":397,"startTime":"2026-05-05T11:24:39.438195400-05:00[America/Bogota]","screenshots":[{"screenshot":"a069bd655c88c07ad299d2b125ef0e88e65f432ffc5faa8a1e3dfa9a14571ca8.png","timeStamp":1777998279835,"screenshotName":"a069bd655c88c07ad299d2b125ef0e88e65f432ffc5faa8a1e3dfa9a14571ca8.png"}],"result":"SUCCESS","precondition":false,"level":2},{"number":9,"description":"Sara clicks on cognito next button","duration":408,"startTime":"2026-05-05T11:24:39.840420800-05:00[America/Bogota]","screenshots":[{"screenshot":"0d0b20885d78e5da66ccd055580c093b639d9859f37d3ebff060513eaac97c9a.png","timeStamp":1777998280249,"screenshotName":"0d0b20885d78e5da66ccd055580c093b639d9859f37d3ebff060513eaac97c9a.png"}],"result":"SUCCESS","precondition":false,"level":2},{"number":10,"description":"Sara enters \u0027Yt7PNg_VnXkvsQ*tPmfi\u0027 into cognito password field","duration":293,"startTime":"2026-05-05T11:24:40.401503-05:00[America/Bogota]","screenshots":[{"screenshot":"9de4434d9c36c22b3a78e5cc367528743e5b6b49ac56dfe539212846f40b88d7.png","timeStamp":1777998280695,"screenshotName":"9de4434d9c36c22b3a78e5cc367528743e5b6b49ac56dfe539212846f40b88d7.png"}],"result":"SUCCESS","precondition":false,"level":2},{"number":11,"description":"Sara clicks on cognito continue button","duration":317,"startTime":"2026-05-05T11:24:40.697476300-05:00[America/Bogota]","screenshots":[{"screenshot":"37f6b6f4aeb47cecf2ad71e98569cc2ad6a16fdd19f17df98c43f9b56a23a6c3.png","timeStamp":1777998281015,"screenshotName":"37f6b6f4aeb47cecf2ad71e98569cc2ad6a16fdd19f17df98c43f9b56a23a6c3.png"}],"result":"SUCCESS","precondition":false,"level":2},{"number":12,"description":"Sara opens the browser at https://asistenciaapp.kit.sura-konecta.com/agent","duration":981,"startTime":"2026-05-05T11:25:01.275495900-05:00[America/Bogota]","screenshots":[{"screenshot":"0725a4f626bfee864fee03c7244afec4f395c08e6c1381211742ea81ff8fb28c.png","timeStamp":1777998302257,"screenshotName":"0725a4f626bfee864fee03c7244afec4f395c08e6c1381211742ea81ff8fb28c.png"}],"result":"SUCCESS","precondition":false,"level":2}]}]},{"number":13,"description":"And navega a agent","duration":6090,"startTime":"2026-05-05T11:25:02.298044-05:00[America/Bogota]","screenshots":[{"screenshot":"6c33328d79bfa8ea64f5ad6ee74552afd428494d330361e36df0b870f435bf53.png","timeStamp":1777998308388,"screenshotName":"6c33328d79bfa8ea64f5ad6ee74552afd428494d330361e36df0b870f435bf53.png"}],"result":"SUCCESS","precondition":false,"level":0,"children":[{"number":14,"description":"Navega a la pagina de agent","duration":6058,"startTime":"2026-05-05T11:25:02.315993500-05:00[America/Bogota]","screenshots":[{"screenshot":"6c33328d79bfa8ea64f5ad6ee74552afd428494d330361e36df0b870f435bf53.png","timeStamp":1777998308374,"screenshotName":"6c33328d79bfa8ea64f5ad6ee74552afd428494d330361e36df0b870f435bf53.png"}],"result":"SUCCESS","precondition":false,"level":1,"children":[{"number":15,"description":"Sara opens the browser at https://asistenciaapp.kit.sura-konecta.com/agent","duration":578,"startTime":"2026-05-05T11:25:02.322993300-05:00[America/Bogota]","screenshots":[{"screenshot":"9b1a2ba5cfb2c7f62bd93bba9cd9e362ce2393de407ceb136ae32e15be82a837.png","timeStamp":1777998302901,"screenshotName":"9b1a2ba5cfb2c7f62bd93bba9cd9e362ce2393de407ceb136ae32e15be82a837.png"}],"result":"SUCCESS","precondition":false,"level":2}]}]},{"number":16,"description":"And diligencia caso express completo desde feature\r\n| departamento_solicita | municipio_solicita | servicios_especiales | gestor_coordinacion | linea | servicio |\r\n| ANTIOQUIA | MEDELLIN | NO | NO | LINEA EJEMPLO 1 | SERVICIO EJEMPLO 1 |","duration":85429,"startTime":"2026-05-05T11:25:08.390344700-05:00[America/Bogota]","exception":{"errorType":"java.lang.AssertionError","message":"\r\nExpected: an element that is visible\r\n     but: no matching element found by [Dirección del destino located with: css: input[name\u003d\u0027data[direccion_del_destino]\u0027]]","stackTrace":[{"declaringClass":"com.sara.automation.interactions.FillCasoExpressFormInOrder","methodName":"llenarCampo","fileName":"FillCasoExpressFormInOrder.java","lineNumber":322},{"declaringClass":"com.sara.automation.interactions.FillCasoExpressFormInOrder","methodName":"llenarDireccionesYUbicacionEnOrden","fileName":"FillCasoExpressFormInOrder.java","lineNumber":284},{"declaringClass":"com.sara.automation.interactions.FillCasoExpressFormInOrder","methodName":"performAs","fileName":"FillCasoExpressFormInOrder.java","lineNumber":88},{"declaringClass":"com.sara.automation.tasks.ClickCasoExpress","methodName":"performAs","fileName":"ClickCasoExpress.java","lineNumber":86},{"declaringClass":"com.sara.automation.stepdefinitions.CasesStepDefinitions","methodName":"completaListasManualesDesdeFeature","fileName":"CasesStepDefinitions.java","lineNumber":91},{"declaringClass":"com.sara.automation.stepdefinitions.CasesStepDefinitions","methodName":"diligenciaCasoExpressCompletoDesdeFeature","fileName":"CasesStepDefinitions.java","lineNumber":105},{"declaringClass":"io.cucumber.java.Invoker","methodName":"doInvoke","fileName":"Invoker.java","lineNumber":66},{"declaringClass":"io.cucumber.java.Invoker","methodName":"invoke","fileName":"Invoker.java","lineNumber":24},{"declaringClass":"io.cucumber.java.AbstractGlueDefinition","methodName":"invokeMethod","fileName":"AbstractGlueDefinition.java","lineNumber":47},{"declaringClass":"io.cucumber.java.JavaStepDefinition","methodName":"execute","fileName":"JavaStepDefinition.java","lineNumber":29},{"declaringClass":"io.cucumber.core.runner.CoreStepDefinition","methodName":"execute","fileName":"CoreStepDefinition.java","lineNumber":66},{"declaringClass":"io.cucumber.core.runner.PickleStepDefinitionMatch","methodName":"runStep","fileName":"PickleStepDefinitionMatch.java","lineNumber":63},{"declaringClass":"io.cucumber.core.runner.TestStep","methodName":"executeStep","fileName":"TestStep.java","lineNumber":85},{"declaringClass":"io.cucumber.core.runner.TestStep","methodName":"run","fileName":"TestStep.java","lineNumber":57},{"declaringClass":"io.cucumber.core.runner.PickleStepTestStep","methodName":"run","fileName":"PickleStepTestStep.java","lineNumber":51},{"declaringClass":"io.cucumber.core.runner.TestCase","methodName":"run","fileName":"TestCase.java","lineNumber":84},{"declaringClass":"io.cucumber.core.runner.Runner","methodName":"runPickle","fileName":"Runner.java","lineNumber":75},{"declaringClass":"io.cucumber.core.runtime.CucumberExecutionContext","methodName":"lambda$runTestCase$5","fileName":"CucumberExecutionContext.java","lineNumber":129},{"declaringClass":"io.cucumber.core.runtime.RethrowingThrowableCollector","methodName":"executeAndThrow","fileName":"RethrowingThrowableCollector.java","lineNumber":23},{"declaringClass":"io.cucumber.core.runtime.CucumberExecutionContext","methodName":"runTestCase","fileName":"CucumberExecutionContext.java","lineNumber":129},{"declaringClass":"io.cucumber.junit.FeatureRunner","methodName":"runChild","fileName":"FeatureRunner.java","lineNumber":144},{"declaringClass":"io.cucumber.junit.FeatureRunner","methodName":"runChild","fileName":"FeatureRunner.java","lineNumber":28},{"declaringClass":"io.cucumber.junit.FeatureRunner","methodName":"run","fileName":"FeatureRunner.java","lineNumber":137},{"declaringClass":"io.cucumber.junit.CucumberSerenityRunner","methodName":"runChild","fileName":"CucumberSerenityRunner.java","lineNumber":259},{"declaringClass":"io.cucumber.junit.CucumberSerenityRunner","methodName":"runChild","fileName":"CucumberSerenityRunner.java","lineNumber":59},{"declaringClass":"worker.org.gradle.process.internal.worker.GradleWorkerMain","methodName":"run","fileName":"GradleWorkerMain.java","lineNumber":69},{"declaringClass":"worker.org.gradle.process.internal.worker.GradleWorkerMain","methodName":"main","fileName":"GradleWorkerMain.java","lineNumber":74}]},"result":"FAILURE","precondition":false,"level":0,"children":[{"number":17,"description":"Abrir Caso Express, seleccionar asistencia, entrar al iframe, habilitar y diligenciar en orden","duration":85398,"startTime":"2026-05-05T11:25:08.412338400-05:00[America/Bogota]","exception":{"errorType":"java.lang.AssertionError","message":"\r\nExpected: an element that is visible\r\n     but: no matching element found by [Dirección del destino located with: css: input[name\u003d\u0027data[direccion_del_destino]\u0027]]","stackTrace":[{"declaringClass":"com.sara.automation.interactions.FillCasoExpressFormInOrder","methodName":"llenarCampo","fileName":"FillCasoExpressFormInOrder.java","lineNumber":322},{"declaringClass":"com.sara.automation.interactions.FillCasoExpressFormInOrder","methodName":"llenarDireccionesYUbicacionEnOrden","fileName":"FillCasoExpressFormInOrder.java","lineNumber":284},{"declaringClass":"com.sara.automation.interactions.FillCasoExpressFormInOrder","methodName":"performAs","fileName":"FillCasoExpressFormInOrder.java","lineNumber":88},{"declaringClass":"com.sara.automation.tasks.ClickCasoExpress","methodName":"performAs","fileName":"ClickCasoExpress.java","lineNumber":86},{"declaringClass":"com.sara.automation.stepdefinitions.CasesStepDefinitions","methodName":"completaListasManualesDesdeFeature","fileName":"CasesStepDefinitions.java","lineNumber":91},{"declaringClass":"com.sara.automation.stepdefinitions.CasesStepDefinitions","methodName":"diligenciaCasoExpressCompletoDesdeFeature","fileName":"CasesStepDefinitions.java","lineNumber":105},{"declaringClass":"io.cucumber.java.Invoker","methodName":"doInvoke","fileName":"Invoker.java","lineNumber":66},{"declaringClass":"io.cucumber.java.Invoker","methodName":"invoke","fileName":"Invoker.java","lineNumber":24},{"declaringClass":"io.cucumber.java.AbstractGlueDefinition","methodName":"invokeMethod","fileName":"AbstractGlueDefinition.java","lineNumber":47},{"declaringClass":"io.cucumber.java.JavaStepDefinition","methodName":"execute","fileName":"JavaStepDefinition.java","lineNumber":29},{"declaringClass":"io.cucumber.core.runner.CoreStepDefinition","methodName":"execute","fileName":"CoreStepDefinition.java","lineNumber":66},{"declaringClass":"io.cucumber.core.runner.PickleStepDefinitionMatch","methodName":"runStep","fileName":"PickleStepDefinitionMatch.java","lineNumber":63},{"declaringClass":"io.cucumber.core.runner.TestStep","methodName":"executeStep","fileName":"TestStep.java","lineNumber":85},{"declaringClass":"io.cucumber.core.runner.TestStep","methodName":"run","fileName":"TestStep.java","lineNumber":57},{"declaringClass":"io.cucumber.core.runner.PickleStepTestStep","methodName":"run","fileName":"PickleStepTestStep.java","lineNumber":51},{"declaringClass":"io.cucumber.core.runner.TestCase","methodName":"run","fileName":"TestCase.java","lineNumber":84},{"declaringClass":"io.cucumber.core.runner.Runner","methodName":"runPickle","fileName":"Runner.java","lineNumber":75},{"declaringClass":"io.cucumber.core.runtime.CucumberExecutionContext","methodName":"lambda$runTestCase$5","fileName":"CucumberExecutionContext.java","lineNumber":129},{"declaringClass":"io.cucumber.core.runtime.RethrowingThrowableCollector","methodName":"executeAndThrow","fileName":"RethrowingThrowableCollector.java","lineNumber":23},{"declaringClass":"io.cucumber.core.runtime.CucumberExecutionContext","methodName":"runTestCase","fileName":"CucumberExecutionContext.java","lineNumber":129},{"declaringClass":"io.cucumber.junit.FeatureRunner","methodName":"runChild","fileName":"FeatureRunner.java","lineNumber":144},{"declaringClass":"io.cucumber.junit.FeatureRunner","methodName":"runChild","fileName":"FeatureRunner.java","lineNumber":28},{"declaringClass":"io.cucumber.junit.FeatureRunner","methodName":"run","fileName":"FeatureRunner.java","lineNumber":137},{"declaringClass":"io.cucumber.junit.CucumberSerenityRunner","methodName":"runChild","fileName":"CucumberSerenityRunner.java","lineNumber":259},{"declaringClass":"io.cucumber.junit.CucumberSerenityRunner","methodName":"runChild","fileName":"CucumberSerenityRunner.java","lineNumber":59},{"declaringClass":"worker.org.gradle.process.internal.worker.GradleWorkerMain","methodName":"run","fileName":"GradleWorkerMain.java","lineNumber":69},{"declaringClass":"worker.org.gradle.process.internal.worker.GradleWorkerMain","methodName":"main","fileName":"GradleWorkerMain.java","lineNumber":74}]},"result":"FAILURE","precondition":false,"level":1,"children":[{"number":18,"description":"Sara clicks on Boton Caso Express","duration":437,"startTime":"2026-05-05T11:25:08.481340400-05:00[America/Bogota]","screenshots":[{"screenshot":"dc4e79c3b641d8a47f29819a27faaf651fce6c9edf06f07027419e24ba69d3b1.png","timeStamp":1777998308918,"screenshotName":"dc4e79c3b641d8a47f29819a27faaf651fce6c9edf06f07027419e24ba69d3b1.png"}],"result":"SUCCESS","precondition":false,"level":2},{"number":19,"description":"Sara clicks on Formulario Creación de Casos (ASISTENCIA)","duration":560,"startTime":"2026-05-05T11:25:08.993018800-05:00[America/Bogota]","screenshots":[{"screenshot":"8215ef1dd57b4ac753324785343b8ea45167bacc9e4452a9f6f30ddf9f289968.png","timeStamp":1777998309553,"screenshotName":"8215ef1dd57b4ac753324785343b8ea45167bacc9e4452a9f6f30ddf9f289968.png"}],"result":"SUCCESS","precondition":false,"level":2},{"number":20,"description":"Sara switch to one script iframe","duration":1225,"startTime":"2026-05-05T11:25:09.570450400-05:00[America/Bogota]","screenshots":[{"screenshot":"3b0bb202ccb0b6319aa1a247847bf9238c8c7b68cf8c3fc408cdeb6795a0859c.png","timeStamp":1777998310796,"screenshotName":"3b0bb202ccb0b6319aa1a247847bf9238c8c7b68cf8c3fc408cdeb6795a0859c.png"}],"result":"SUCCESS","precondition":false,"level":2},{"number":21,"description":"Sara fill caso express form in order","duration":71628,"startTime":"2026-05-05T11:25:22.165709100-05:00[America/Bogota]","screenshots":[{"screenshot":"085a570fe86e8ac14f8ed6f1054784d9e8c5c755869805ff87a7011b1646c712.png","htmlSource":"pagesource249200403944690600.html","timeStamp":1777998393789,"screenshotName":"085a570fe86e8ac14f8ed6f1054784d9e8c5c755869805ff87a7011b1646c712.png"}],"exception":{"errorType":"java.lang.AssertionError","message":"\r\nExpected: an element that is visible\r\n     but: no matching element found by [Dirección del destino located with: css: input[name\u003d\u0027data[direccion_del_destino]\u0027]]","stackTrace":[{"declaringClass":"com.sara.automation.interactions.FillCasoExpressFormInOrder","methodName":"llenarCampo","fileName":"FillCasoExpressFormInOrder.java","lineNumber":322},{"declaringClass":"com.sara.automation.interactions.FillCasoExpressFormInOrder","methodName":"llenarDireccionesYUbicacionEnOrden","fileName":"FillCasoExpressFormInOrder.java","lineNumber":284},{"declaringClass":"com.sara.automation.interactions.FillCasoExpressFormInOrder","methodName":"performAs","fileName":"FillCasoExpressFormInOrder.java","lineNumber":88},{"declaringClass":"com.sara.automation.tasks.ClickCasoExpress","methodName":"performAs","fileName":"ClickCasoExpress.java","lineNumber":86},{"declaringClass":"com.sara.automation.stepdefinitions.CasesStepDefinitions","methodName":"completaListasManualesDesdeFeature","fileName":"CasesStepDefinitions.java","lineNumber":91},{"declaringClass":"com.sara.automation.stepdefinitions.CasesStepDefinitions","methodName":"diligenciaCasoExpressCompletoDesdeFeature","fileName":"CasesStepDefinitions.java","lineNumber":105},{"declaringClass":"io.cucumber.java.Invoker","methodName":"doInvoke","fileName":"Invoker.java","lineNumber":66},{"declaringClass":"io.cucumber.java.Invoker","methodName":"invoke","fileName":"Invoker.java","lineNumber":24},{"declaringClass":"io.cucumber.java.AbstractGlueDefinition","methodName":"invokeMethod","fileName":"AbstractGlueDefinition.java","lineNumber":47},{"declaringClass":"io.cucumber.java.JavaStepDefinition","methodName":"execute","fileName":"JavaStepDefinition.java","lineNumber":29},{"declaringClass":"io.cucumber.core.runner.CoreStepDefinition","methodName":"execute","fileName":"CoreStepDefinition.java","lineNumber":66},{"declaringClass":"io.cucumber.core.runner.PickleStepDefinitionMatch","methodName":"runStep","fileName":"PickleStepDefinitionMatch.java","lineNumber":63},{"declaringClass":"io.cucumber.core.runner.TestStep","methodName":"executeStep","fileName":"TestStep.java","lineNumber":85},{"declaringClass":"io.cucumber.core.runner.TestStep","methodName":"run","fileName":"TestStep.java","lineNumber":57},{"declaringClass":"io.cucumber.core.runner.PickleStepTestStep","methodName":"run","fileName":"PickleStepTestStep.java","lineNumber":51},{"declaringClass":"io.cucumber.core.runner.TestCase","methodName":"run","fileName":"TestCase.java","lineNumber":84},{"declaringClass":"io.cucumber.core.runner.Runner","methodName":"runPickle","fileName":"Runner.java","lineNumber":75},{"declaringClass":"io.cucumber.core.runtime.CucumberExecutionContext","methodName":"lambda$runTestCase$5","fileName":"CucumberExecutionContext.java","lineNumber":129},{"declaringClass":"io.cucumber.core.runtime.RethrowingThrowableCollector","methodName":"executeAndThrow","fileName":"RethrowingThrowableCollector.java","lineNumber":23},{"declaringClass":"io.cucumber.core.runtime.CucumberExecutionContext","methodName":"runTestCase","fileName":"CucumberExecutionContext.java","lineNumber":129},{"declaringClass":"io.cucumber.junit.FeatureRunner","methodName":"runChild","fileName":"FeatureRunner.java","lineNumber":144},{"declaringClass":"io.cucumber.junit.FeatureRunner","methodName":"runChild","fileName":"FeatureRunner.java","lineNumber":28},{"declaringClass":"io.cucumber.junit.FeatureRunner","methodName":"run","fileName":"FeatureRunner.java","lineNumber":137},{"declaringClass":"io.cucumber.junit.CucumberSerenityRunner","methodName":"runChild","fileName":"CucumberSerenityRunner.java","lineNumber":259},{"declaringClass":"io.cucumber.junit.CucumberSerenityRunner","methodName":"runChild","fileName":"CucumberSerenityRunner.java","lineNumber":59},{"declaringClass":"worker.org.gradle.process.internal.worker.GradleWorkerMain","methodName":"run","fileName":"GradleWorkerMain.java","lineNumber":69},{"declaringClass":"worker.org.gradle.process.internal.worker.GradleWorkerMain","methodName":"main","fileName":"GradleWorkerMain.java","lineNumber":74}]},"result":"FAILURE","precondition":false,"level":2,"children":[{"number":22,"description":"Sara enters \u0027Calle 19 #64-50\u0027 into Dirección servicio","duration":320,"startTime":"2026-05-05T11:26:11.671290100-05:00[America/Bogota]","screenshots":[{"screenshot":"79bdd2130e63d0914c357bb674d88f4b0a877fbe47f6bd77e1b145dda7788f3b.png","timeStamp":1777998371991,"screenshotName":"79bdd2130e63d0914c357bb674d88f4b0a877fbe47f6bd77e1b145dda7788f3b.png"}],"result":"SUCCESS","precondition":false,"level":3}]}]}]},{"number":23,"description":"And diligenciamos el proveedor\r\n| Nombre del proveedor | Servicio |\r\n| PROVEEDOR PRUEBA | TOMA SERVICIO |","duration":5,"startTime":"2026-05-05T11:26:33.841886300-05:00[America/Bogota]","result":"SKIPPED","precondition":false,"level":0},{"number":24,"description":"And transicionamos los estados del caso","duration":4,"startTime":"2026-05-05T11:26:33.849883600-05:00[America/Bogota]","result":"SKIPPED","precondition":false,"level":0},{"number":25,"description":"Then deberia ver la ruta agent","duration":4,"startTime":"2026-05-05T11:26:33.855883900-05:00[America/Bogota]","result":"SKIPPED","precondition":false,"level":0}],"userStory":{"id":"apertura-de-la-pagina-de-casos","storyName":"Apertura de la pagina de casos","displayName":"Apertura de la pagina de casos","path":"cases/open_cases.feature","narrative":"  Como equipo de automatizacion\n  Quiero abrir la pagina de casos\n  Para validar que la URL es accesible","type":"feature"},"featureTag":{"name":"Cases/Apertura de la pagina de casos","type":"feature","displayName":"Cases/Apertura de la pagina de casos"},"title":"Abrir la URL, loguearse y navegar a agent","description":"","tags":[{"name":"Cases","type":"capability","displayName":"Cases"},{"name":"Cases/Apertura de la pagina de casos","type":"feature","displayName":"Apertura de la pagina de casos"}],"startTime":"2026-05-05T11:24:26.873255100-05:00[America/Bogota]","duration":126999,"testFailureCause":{"errorType":"java.lang.AssertionError","message":"\r\nExpected: an element that is visible\r\n     but: no matching element found by [Dirección del destino located with: css: input[name\u003d\u0027data[direccion_del_destino]\u0027]]","stackTrace":[{"declaringClass":"com.sara.automation.interactions.FillCasoExpressFormInOrder","methodName":"llenarCampo","fileName":"FillCasoExpressFormInOrder.java","lineNumber":322},{"declaringClass":"com.sara.automation.interactions.FillCasoExpressFormInOrder","methodName":"llenarDireccionesYUbicacionEnOrden","fileName":"FillCasoExpressFormInOrder.java","lineNumber":284},{"declaringClass":"com.sara.automation.interactions.FillCasoExpressFormInOrder","methodName":"performAs","fileName":"FillCasoExpressFormInOrder.java","lineNumber":88},{"declaringClass":"com.sara.automation.tasks.ClickCasoExpress","methodName":"performAs","fileName":"ClickCasoExpress.java","lineNumber":86},{"declaringClass":"com.sara.automation.stepdefinitions.CasesStepDefinitions","methodName":"completaListasManualesDesdeFeature","fileName":"CasesStepDefinitions.java","lineNumber":91},{"declaringClass":"com.sara.automation.stepdefinitions.CasesStepDefinitions","methodName":"diligenciaCasoExpressCompletoDesdeFeature","fileName":"CasesStepDefinitions.java","lineNumber":105},{"declaringClass":"io.cucumber.java.Invoker","methodName":"doInvoke","fileName":"Invoker.java","lineNumber":66},{"declaringClass":"io.cucumber.java.Invoker","methodName":"invoke","fileName":"Invoker.java","lineNumber":24},{"declaringClass":"io.cucumber.java.AbstractGlueDefinition","methodName":"invokeMethod","fileName":"AbstractGlueDefinition.java","lineNumber":47},{"declaringClass":"io.cucumber.java.JavaStepDefinition","methodName":"execute","fileName":"JavaStepDefinition.java","lineNumber":29},{"declaringClass":"io.cucumber.core.runner.CoreStepDefinition","methodName":"execute","fileName":"CoreStepDefinition.java","lineNumber":66},{"declaringClass":"io.cucumber.core.runner.PickleStepDefinitionMatch","methodName":"runStep","fileName":"PickleStepDefinitionMatch.java","lineNumber":63},{"declaringClass":"io.cucumber.core.runner.TestStep","methodName":"executeStep","fileName":"TestStep.java","lineNumber":85},{"declaringClass":"io.cucumber.core.runner.TestStep","methodName":"run","fileName":"TestStep.java","lineNumber":57},{"declaringClass":"io.cucumber.core.runner.PickleStepTestStep","methodName":"run","fileName":"PickleStepTestStep.java","lineNumber":51},{"declaringClass":"io.cucumber.core.runner.TestCase","methodName":"run","fileName":"TestCase.java","lineNumber":84},{"declaringClass":"io.cucumber.core.runner.Runner","methodName":"runPickle","fileName":"Runner.java","lineNumber":75},{"declaringClass":"io.cucumber.core.runtime.CucumberExecutionContext","methodName":"lambda$runTestCase$5","fileName":"CucumberExecutionContext.java","lineNumber":129},{"declaringClass":"io.cucumber.core.runtime.RethrowingThrowableCollector","methodName":"executeAndThrow","fileName":"RethrowingThrowableCollector.java","lineNumber":23},{"declaringClass":"io.cucumber.core.runtime.CucumberExecutionContext","methodName":"runTestCase","fileName":"CucumberExecutionContext.java","lineNumber":129},{"declaringClass":"io.cucumber.junit.FeatureRunner","methodName":"runChild","fileName":"FeatureRunner.java","lineNumber":144},{"declaringClass":"io.cucumber.junit.FeatureRunner","methodName":"runChild","fileName":"FeatureRunner.java","lineNumber":28},{"declaringClass":"io.cucumber.junit.FeatureRunner","methodName":"run","fileName":"FeatureRunner.java","lineNumber":137},{"declaringClass":"io.cucumber.junit.CucumberSerenityRunner","methodName":"runChild","fileName":"CucumberSerenityRunner.java","lineNumber":259},{"declaringClass":"io.cucumber.junit.CucumberSerenityRunner","methodName":"runChild","fileName":"CucumberSerenityRunner.java","lineNumber":59},{"declaringClass":"worker.org.gradle.process.internal.worker.GradleWorkerMain","methodName":"run","fileName":"GradleWorkerMain.java","lineNumber":69},{"declaringClass":"worker.org.gradle.process.internal.worker.GradleWorkerMain","methodName":"main","fileName":"GradleWorkerMain.java","lineNumber":74}]},"testFailureClassname":"java.lang.AssertionError","testFailureMessage":"\r\nExpected: an element that is visible\r\n     but: no matching element found by [Dirección del destino located with: css: input[name\u003d\u0027data[direccion_del_destino]\u0027]]","testFailureSummary":"FAILURE;java.lang.AssertionError;\r\nExpected: an element that is visible\r\n     but: no matching element found by [Dirección del destino located with: css: input[name\u003d\u0027data[direccion_del_destino]\u0027]];FillCasoExpressFormInOrder.java","projectKey":"","annotatedResult":"FAILURE","sessionId":"eb1bb1a232954c76b03cf5ad99eef8f2","driver":"chrome","isManualTestingUpToDate":false,"manual":false,"testSource":"Cucumber","actors":[{"name":"Sara","can":["browse the web"]}],"result":"FAILURE"}